<?xml version="1.0"?>
<persons>
  <persons>
    <idPerson>AF1A60</idPerson>
    <lastName>Faber</lastName>
    <firstName>Race</firstName>
    <address>
      <street>2 Buell Trail</street>
      <city>Irvine</city>
      <state>CA</state>
      <zipCode>92710</zipCode>
      <country>US</country>
    </address>
    <email>
      <string>frace7@ning.com</string>
    </email>
  </persons>
  <persons>
    <idPerson>AF1A58</idPerson>
    <lastName>Amy</lastName>
    <firstName>Jenton</firstName>
    <address>
      <street>501 Kennedy Pass</street>
      <city>San Jose</city>
      <state>CA</state>
      <zipCode>95194</zipCode>
      <country>US</country>
    </address>
    <email>
      <string>ajenton5@eepurl.com</string>
      <string>potteralex457@yahoo.com</string>
      <string>potteralex457@red.com</string>
      <string>potteralex457@witcher.com</string>
    </email>
  </persons>
  <persons>
    <idPerson>AF1A59</idPerson>
    <lastName>Elsbeth</lastName>
    <firstName>Reveley</firstName>
    <address>
      <street>80 Shasta Alley</street>
      <city>Salt Lake City</city>
      <state>UT</state>
      <zipCode>84189</zipCode>
      <country>US</country>
    </address>
    <email>
      <string>ereveley6@upenn.edu</string>
      <string>gerad.Harad1009@this.com</string>
      <string>gerad.Harad1009@that.com</string>
    </email>
  </persons>
  <persons>
    <idPerson>AF1A54</idPerson>
    <lastName>Candie</lastName>
    <firstName>Crannage</firstName>
    <address>
      <street>3896 Shelley Terrace</street>
      <city>Gaithersburg</city>
      <state>MD</state>
      <zipCode>20883</zipCode>
      <country>US</country>
    </address>
    <email>
      <string>ccrannage1@digg.com</string>
      <string>minamiCrimson@gmail.com</string>
      <string>crimsonQueen@yahoo.com.vn</string>
    </email>
  </persons>
  <persons>
    <idPerson>AF1A55</idPerson>
    <lastName>Randal</lastName>
    <firstName>Briddle</firstName>
    <address>
      <street>56059 Hollow Ridge Court</street>
      <city>Lees Summit</city>
      <state>MO</state>
      <zipCode>64082</zipCode>
      <country>US</country>
    </address>
    <email>
      <string>rbriddle2@networkadvertising.org</string>
      <string>thisisme117@yahoo.com</string>
    </email>
  </persons>
  <persons>
    <idPerson>AF1A56</idPerson>
    <lastName>Corbin</lastName>
    <firstName>Brine</firstName>
    <address>
      <street>2 Canary Lane</street>
      <city>Washington</city>
      <state>DC</state>
      <zipCode>20268</zipCode>
      <country>US</country>
    </address>
    <email>
      <string>cbrine3@webnode.com</string>
      <string>forVahala1992@crystal.com</string>
      <string>skyrimBelongtotheNord666@gmail.com</string>
    </email>
  </persons>
  <persons>
    <idPerson>AF1A57</idPerson>
    <lastName>Reece</lastName>
    <firstName>Haggerwood</firstName>
    <address>
      <street>19211 Maywood Circle</street>
      <city>Vancouver</city>
      <state>WA</state>
      <zipCode>98687</zipCode>
      <country>US</country>
    </address>
    <email>
      <string>rhaggerwood4@histats.com</string>
    </email>
  </persons>
  <persons>
    <idPerson>AF1A61</idPerson>
    <lastName>Berk</lastName>
    <firstName>Meanwell</firstName>
    <address>
      <street>651 Florence Junction</street>
      <city>Greensboro</city>
      <state>NC</state>
      <zipCode>27404</zipCode>
      <country>US</country>
    </address>
    <email>
      <string>bmeanwell8@parallels.com</string>
    </email>
  </persons>
  <persons>
    <idPerson>AF1A62</idPerson>
    <lastName>Prentiss</lastName>
    <firstName>Dungey</firstName>
    <address>
      <street>41 Bluestem Terrace</street>
      <city>Washington</city>
      <state>DC</state>
      <zipCode>20057</zipCode>
      <country>US</country>
    </address>
    <email>
      <string>pdungey9@hubpages.com</string>
      <string>tobeOrnottoBe1092@engineering.com</string>
      <string>sjlkThesia@hmail.com</string>
      <string>universal76forthis09@haha.com</string>
    </email>
  </persons>
  <persons>
    <idPerson>AF1A63</idPerson>
    <lastName>Hermia</lastName>
    <firstName>Bunford</firstName>
    <address>
      <street>2306 Stang Court</street>
      <city>Newark</city>
      <state>DE</state>
      <zipCode>19714</zipCode>
      <country>US</country>
    </address>
    <email>
      <string>hbunforda@businesswire.com</string>
      <string>thisisit918@yahoo.com</string>
      <string>nowhere134@gmail.com</string>
    </email>
  </persons>
  <persons>
    <idPerson>AF1A53</idPerson>
    <lastName>Terrance</lastName>
    <firstName>Rayman</firstName>
    <address>
      <street>2 Hauk Alley</street>
      <city>Monticello</city>
      <state>MN</state>
      <zipCode>55565</zipCode>
      <country>US</country>
    </address>
    <email>
      <string>trayman0@sitemeter.com</string>
      <string>squarry0@salon.com</string>
    </email>
  </persons>
  <persons>
    <idPerson>AF1A64</idPerson>
    <lastName>Nollie</lastName>
    <firstName>Blesdill</firstName>
    <address>
      <street>2 Loftsgordon Drive</street>
      <city>Erie</city>
      <state>PA</state>
      <zipCode>16550</zipCode>
      <country>US</country>
    </address>
    <email>
      <string>nblesdillb@harvard.edu</string>
      <string>iamNotaBot9018@facebook.com</string>
    </email>
  </persons>
</persons>
